misc/__init__.py
misc/combine_pictures.py
misc/merge_dataset.py
misc/split_dataset.py
remback/__init__.py
remback/cli.py
remback/remover.py
remback/utils.py
remback/sam_models/__init__.py
remback/sam_models/build_sam.py
remback/sam_models/common.py
remback/sam_models/image_encoder.py
remback/sam_models/mask_decoder.py
remback/sam_models/predictor.py
remback/sam_models/prompt_encoder.py
remback/sam_models/sam.py
remback/sam_models/transformer.py
remback/sam_models/utils/__init__.py
remback/sam_models/utils/transforms.py
train/__init__.py
train/fine_tune_sam_v1.py
train/fine_tune_sam_v2.py
validation/__init__.py
validation/validation.py
remback-0.0.2.dist-info/METADATA
remback-0.0.2.dist-info/WHEEL
remback-0.0.2.dist-info/entry_points.txt
remback-0.0.2.dist-info/top_level.txt
remback-0.0.2.dist-info/RECORD
