Metadata-Version: 2.4
Name: remback
Version: 0.0.2
Summary: Face‑aware background removal with a fine‑tuned SAM.
Home-page: https://github.com/duriantaco/remback
Author: oha
Author-email: oha <aaronoh2015@gmail.com>
License: MIT
Requires-Python: >=3.10,<3.12
Requires-Dist: torch>=2.0
Requires-Dist: opencv-python>=4.8
Requires-Dist: numpy>=1.26.4
Requires-Dist: mtcnn>=1.0.0
Requires-Dist: tensorflow>=2.19.0
Requires-Dist: torchvision>=0.15.1
Requires-Dist: torchaudio>=2.0.1
Requires-Dist: tqdm>=4.65.2
Requires-Dist: huggingface_hub>=0.10.0
Dynamic: author
Dynamic: home-page
Dynamic: requires-python
